sequdas_qc/__init__.py
sequdas_qc/kaiju_parse.py
sequdas_qc/kraken_parse.py
sequdas_qc/sequdas_qc.py
sequdas_qc/Config/config.ini
sequdas_qc/Lib/__init__.py
sequdas_qc/Lib/core.py
sequdas_qc/Lib/message.py
sequdas_qc/Lib/pipe.py
sequdas_qc/Lib/sample_sheet.py
sequdas_qc/Lib/status_db.py
sequdas_qc/Lib/status_log.py
sequdas_qc-1.0.1.dist-info/LICENSE
sequdas_qc-1.0.1.dist-info/METADATA
sequdas_qc-1.0.1.dist-info/WHEEL
sequdas_qc-1.0.1.dist-info/entry_points.txt
sequdas_qc-1.0.1.dist-info/top_level.txt
sequdas_qc-1.0.1.dist-info/RECORD
