Metadata-Version: 2.1
Name: sequdas-qc
Version: 1.0.1
Summary: Sequence Upload and Data Archiving System
Home-page: https://github.com/duanjunhyq/sequdas_qc
Author: Jun Duan
Author-email: jun.duan@bccdc.ca
License: MIT
Keywords: NGS sequence archive analysis
Platform: UNKNOWN
Classifier: Programming Language :: Python :: 3
Classifier: License :: OSI Approved :: MIT License
Classifier: Operating System :: OS Independent
Requires-Python: >=3.6
Requires-Dist: configparser
Requires-Dist: mysql-connector-python
Requires-Dist: pytz
Requires-Dist: ntplib
Requires-Dist: validate-email
